LICENSE
LICENSE.fr
les_stats/__init__.py
les_stats/client_api/client.py
les_stats/client_api/riot.py
les_stats/main.py
les_stats/metrics/generic/metrics.py
les_stats/metrics/internal/metrics.py
les_stats/metrics/lol/metrics.py
les_stats/metrics/lol/utils.py
les_stats/metrics/main.py
les_stats/metrics/metrics.py
les_stats/metrics/tft/metrics.py
les_stats/metrics/tft/utils.py
les_stats/metrics/valorant/metrics.py
les_stats/metrics/valorant/utils.py
les_stats/models/__init__.py
les_stats/models/internal/auth.py
les_stats/models/internal/event.py
les_stats/models/internal/stage.py
les_stats/models/internal/tournament.py
les_stats/models/lol/game.py
les_stats/models/tft/game.py
les_stats/models/valorant/game.py
les_stats/routers/__init__.py
les_stats/routers/api.py
les_stats/routers/internal/api.py
les_stats/routers/internal/event.py
les_stats/routers/internal/stage.py
les_stats/routers/internal/tournament.py
les_stats/routers/lol/api.py
les_stats/routers/lol/game.py
les_stats/routers/tft/api.py
les_stats/routers/tft/game.py
les_stats/routers/tft/stat.py
les_stats/routers/tft/summoner.py
les_stats/routers/valorant/api.py
les_stats/routers/valorant/game.py
les_stats/schemas/client_api/data.py
les_stats/schemas/internal/event.py
les_stats/schemas/internal/generic.py
les_stats/schemas/internal/stage.py
les_stats/schemas/internal/tournament.py
les_stats/schemas/riot/game.py
les_stats/schemas/tft/stat.py
les_stats/statics/favicon.ico
les_stats/utils/auth.py
les_stats/utils/config.py
les_stats/utils/db.py
les_stats/utils/import_match.py
les_stats/utils/internal.py
les_stats/utils/status.py
les_stats-0.3.1.dist-info/METADATA
les_stats-0.3.1.dist-info/LICENSE.fr
les_stats-0.3.1.dist-info/LICENSE
les_stats-0.3.1.dist-info/WHEEL
les_stats-0.3.1.dist-info/RECORD
