Metadata-Version: 2.1
Name: les-stats
Version: 0.3.1
Summary: Tournament statistics
Home-page: https://github.com/lyon-esport/stats
License: CeCILL
Keywords: lol,esport,statistics
Author: Ludovic Ortega
Author-email: ludovic.ortega@lyon-esport.fr
Requires-Python: >=3.8,<4.0
Classifier: License :: OSI Approved :: CEA CNRS Inria Logiciel Libre License, version 2.1 (CeCILL-2.1)
Classifier: License :: Other/Proprietary License
Classifier: Operating System :: OS Independent
Classifier: Programming Language :: Python
Classifier: Programming Language :: Python :: 3
Classifier: Programming Language :: Python :: 3.8
Classifier: Programming Language :: Python :: 3.9
Classifier: Programming Language :: Python :: 3.10
Classifier: Programming Language :: Python :: 3.11
Classifier: Programming Language :: Python :: 3.10
Classifier: Programming Language :: Python :: 3.11
Classifier: Programming Language :: Python :: 3.8
Classifier: Programming Language :: Python :: 3.9
Classifier: Topic :: Utilities
Requires-Dist: asyncclick (>=8.1.3.4,<9.0.0.0)
Requires-Dist: colorama (>=0.4.6,<0.5.0) ; sys_platform == "win32"
Requires-Dist: fastapi[all] (>=0.88.0,<0.89.0)
Requires-Dist: httpx (>=0.23.1,<0.24.0)
Requires-Dist: prometheus-client (>=0.15.0,<0.16.0)
Requires-Dist: sentry-sdk (>=1.11.1,<2.0.0)
Requires-Dist: tortoise-orm (>=0.19.2,<0.20.0)
Requires-Dist: uvicorn[standard] (>=0.20.0,<0.21.0)
Project-URL: Repository, https://github.com/lyon-esport/stats
